powerbox/__init__.py
powerbox/_version.py
powerbox/dft.py
powerbox/dft_backend.py
powerbox/powerbox.py
powerbox/tools.py
powerbox-0.8.2.dist-info/LICENSE.rst
powerbox-0.8.2.dist-info/METADATA
powerbox-0.8.2.dist-info/WHEEL
powerbox-0.8.2.dist-info/top_level.txt
powerbox-0.8.2.dist-info/RECORD
