Metadata-Version: 2.1
Name: powerbox
Version: 0.8.2
Summary: Create arbitrary boxes with isotropic power spectra
Author-email: Steven Murray <steven.g.murray@asu.edu>
License: MIT
Project-URL: repository, https://github.com/steven-murray/powerbox
Project-URL: documentation, https://powerbox.readthedocs.io
Keywords: power-spectrum,signal processing
Classifier: Programming Language :: Python :: 3
Requires-Python: >=3.9
License-File: LICENSE.rst
Requires-Dist: numpy >1.6.2
Provides-Extra: all
Requires-Dist: powerbox[dev] ; extra == 'all'
Provides-Extra: dev
Requires-Dist: powerbox[docs,fftw,tests] ; extra == 'dev'
Requires-Dist: pre-commit ; extra == 'dev'
Provides-Extra: docs
Requires-Dist: sphinx ; extra == 'docs'
Requires-Dist: numpydoc ; extra == 'docs'
Requires-Dist: nbsphinx ; extra == 'docs'
Requires-Dist: ipykernel ; extra == 'docs'
Requires-Dist: pandoc ; extra == 'docs'
Requires-Dist: sphinx-rtd-theme ; extra == 'docs'
Requires-Dist: sphinx-automodapi ==0.7 ; extra == 'docs'
Requires-Dist: matplotlib ; extra == 'docs'
Requires-Dist: hmf ; extra == 'docs'
Requires-Dist: packaging ; extra == 'docs'
Provides-Extra: fftw
Requires-Dist: pyfftw ; extra == 'fftw'
Provides-Extra: tests
Requires-Dist: wheel ; extra == 'tests'
Requires-Dist: flake8 ; extra == 'tests'
Requires-Dist: pytest ; extra == 'tests'
Requires-Dist: pytest-cov ; extra == 'tests'
Requires-Dist: scipy ; extra == 'tests'
